projects_parser/__init__.py
projects_parser/main.py
projects_parser/prompts.py
projects_parser-2025.12.21120037.dist-info/METADATA
projects_parser-2025.12.21120037.dist-info/WHEEL
projects_parser-2025.12.21120037.dist-info/top_level.txt
projects_parser-2025.12.21120037.dist-info/RECORD
