Metadata-Version: 2.4
Name: projects-parser
Version: 2025.12.21120037
Summary: A new package that leverages advanced pattern matching with retries to process user-submitted project titles and descriptions, extracting structured insights such as the project name, programming lang
Author-email: projects-parser <hi@eugene.plus>
License: MIT
Project-URL: Homepage, https://github.com/chigwell/projects-parser
Requires-Python: >=3.9
Requires-Dist: langchain-llm7>=0.0.0
Requires-Dist: llmatch-messages>=0.0.0
Requires-Dist: langchain-core>=0.3.0
